registrator/__init__.py
registrator/channel.py
registrator/image.py
registrator/tests/test_data/IMG.jpg
registrator/tests/test_data/imUV.tif
registrator/tests/test_data/imch0.tif
registrator/tests/test_data/imch1.tif
registrator/tests/test_data/imch2.tif
registrator/tests/test_data/imch3.tif
registrator-0.1.3.dist-info/METADATA
registrator-0.1.3.dist-info/WHEEL
registrator-0.1.3.dist-info/top_level.txt
registrator-0.1.3.dist-info/RECORD
