Metadata-Version: 2.1
Name: registrator
Version: 0.1.3
Summary: Register images of microfluidics channels
Home-page: https://github.com/impact27/registrator
Author: Quentin Peter
Author-email: qaep2@cam.ac.uk
License: GPl v3
Keywords: image registration microfluidics
Platform: UNKNOWN
Classifier: Development Status :: 4 - Beta
Classifier: License :: OSI Approved :: GNU General Public License v3 or later (GPLv3+)
Classifier: Programming Language :: Python :: 3 :: Only
Classifier: Topic :: Scientific/Engineering
Requires-Dist: numpy
Requires-Dist: scipy
Requires-Dist: opencv-python
